cython_uvp6.cpython-38-x86_64-linux-gnu.so
uvpec-1.0.0.dist-info/top_level.txt
uvpec-1.0.0.dist-info/WHEEL
uvpec-1.0.0.dist-info/RECORD
uvpec-1.0.0.dist-info/entry_points.txt
uvpec-1.0.0.dist-info/METADATA
uvpec-1.0.0.dist-info/LICENSE
uvpec/custom.py
uvpec/weights.py
uvpec/__init__.py
uvpec/log.py
uvpec/save_cross_validation.py
uvpec/cross_validation.py
uvpec/config.yaml
uvpec/sample_detritus.py
uvpec/create_taxoconf.py
uvpec/save_model.py
uvpec/train.py
uvpec/extract_features.py
uvpec/__main__.py
uvpec/evaluate.py
uvpec/configure.py
