Metadata-Version: 2.1
Name: uvpec
Version: 1.0.0
Summary: Underwater Vision Profiler Embedded Classifier
Home-page: https://github.com/ecotaxa/uvpec
Author: Florian Ricour
Author-email: Florian Ricour <uvpec.5ppdz@aleeas.com>
Project-URL: homepage, https://github.com/ecotaxa/uvpec
Classifier: Development Status :: 3 - Alpha
Classifier: Programming Language :: Python :: 3
Requires-Python: >=3.6
License-File: LICENSE
Requires-Dist: numpy >=1.20.3
Requires-Dist: pandas >=1.2.1
Requires-Dist: PyYaml >=5.3.1
Requires-Dist: scikit-image >=0.18.1
Requires-Dist: xgboost >=1.3.3
Requires-Dist: scikit-learn >=1.3.0
Requires-Dist: pyarrow >=7.0.0
Requires-Dist: key-generator >=1.0.3
Requires-Dist: pillow >=8.2.2
Requires-Dist: matplotlib >=3.3.4
Requires-Dist: seaborn >=0.11.1
